LingzuWenkuBuquan/README.md
LingzuWenkuBuquan/__init__.py
LingzuWenkuBuquan/__main__.py
LingzuWenkuBuquan/file.epub
LingzuWenkuBuquan/index.html
LingzuWenkuBuquan/css/__init__.py
LingzuWenkuBuquan/css/annotations.css
LingzuWenkuBuquan/css/main.css
LingzuWenkuBuquan/css/normalize.css
LingzuWenkuBuquan/css/popup.css
LingzuWenkuBuquan/font/__init__.py
LingzuWenkuBuquan/font/fontello.eot
LingzuWenkuBuquan/font/fontello.svg
LingzuWenkuBuquan/font/fontello.ttf
LingzuWenkuBuquan/font/fontello.woff
LingzuWenkuBuquan/img/__init__.py
LingzuWenkuBuquan/img/annotator-glyph-sprite.png
LingzuWenkuBuquan/img/annotator-icon-sprite.png
LingzuWenkuBuquan/img/apple-touch-icon.png
LingzuWenkuBuquan/img/cancelfullscreen.png
LingzuWenkuBuquan/img/close.png
LingzuWenkuBuquan/img/fullscreen.png
LingzuWenkuBuquan/img/loader.gif
LingzuWenkuBuquan/img/menu-icon.png
LingzuWenkuBuquan/img/save.png
LingzuWenkuBuquan/img/saved.png
LingzuWenkuBuquan/img/settings-s.png
LingzuWenkuBuquan/img/settings.png
LingzuWenkuBuquan/img/star.png
LingzuWenkuBuquan/js/__init__.py
LingzuWenkuBuquan/js/epub.js
LingzuWenkuBuquan/js/epub.min.js
LingzuWenkuBuquan/js/epub.min.map
LingzuWenkuBuquan/js/hooks.min.js
LingzuWenkuBuquan/js/hooks.min.map
LingzuWenkuBuquan/js/reader.js
LingzuWenkuBuquan/js/reader.js.map
LingzuWenkuBuquan/js/reader.min.js
LingzuWenkuBuquan/js/reader.min.map
LingzuWenkuBuquan/js/hooks/__init__.py
LingzuWenkuBuquan/js/hooks/extensions/__init__.py
LingzuWenkuBuquan/js/hooks/extensions/highlight.js
LingzuWenkuBuquan/js/libs/__init__.py
LingzuWenkuBuquan/js/libs/jquery.min.js
LingzuWenkuBuquan/js/libs/localforage.min.js
LingzuWenkuBuquan/js/libs/screenfull.js
LingzuWenkuBuquan/js/libs/screenfull.min.js
LingzuWenkuBuquan/js/libs/zip.min.js
LingzuWenkuBuquan/js/plugins/__init__.py
LingzuWenkuBuquan/js/plugins/hypothesis.js
LingzuWenkuBuquan/js/plugins/search.js
lingzu_wenku_buquan-2024.3.5.0.dist-info/METADATA
lingzu_wenku_buquan-2024.3.5.0.dist-info/WHEEL
lingzu_wenku_buquan-2024.3.5.0.dist-info/entry_points.txt
lingzu_wenku_buquan-2024.3.5.0.dist-info/top_level.txt
lingzu_wenku_buquan-2024.3.5.0.dist-info/RECORD
